bayespropestimation/__init__.py
bayespropestimation/bayespropestimation.py
bayespropestimation/bayesprophelpers.py
bayespropestimation/bayespropplotters.py
bayespropestimation-0.9.3.dist-info/LICENSE
bayespropestimation-0.9.3.dist-info/METADATA
bayespropestimation-0.9.3.dist-info/WHEEL
bayespropestimation-0.9.3.dist-info/top_level.txt
bayespropestimation-0.9.3.dist-info/RECORD
